safenote/__init__.py
safenote-0.1.5.dist-info/WHEEL
safenote-0.1.5.dist-info/METADATA
safenote-0.1.5.dist-info/RECORD
