Metadata-Version: 2.1
Name: safenote
Version: 0.1.5
Summary: SafeNote (Safe Notebook) is a tool for injecting your secrets into Jupyter notebooks environment safer and easier.
Home-page: https://safenote.lingxi.li/
Author: Lingxi Li
Author-email: lilingxi01@gmail.com
Requires-Python: >=3.8,<4
Classifier: Programming Language :: Python :: 3
Classifier: Programming Language :: Python :: 3.8
Classifier: Programming Language :: Python :: 3.9
Classifier: Programming Language :: Python :: 3.10
Classifier: Programming Language :: Python :: 3.11
Project-URL: Repository, https://github.com/lilingxi01/safenote
